{
    "career":"Recruit",
    "species":"male",
    "health":10,
    "stamina":10,
    "weight":2,
    "signs":["midbun","scarf"],
    "gears":[["sword","53"]],
    "orders":[
        {"key":"w","action":"walk"},
        {"key":"a","action":"turnLeft"},
        {"key":"d","action":"turnRigh"},
        {"key":"z","action":"spur"},
        {"key":"x","action":"hack"},
        {"key":"c","action":"swep"}
    ],
    "skills":[
        {
            "name":"spur",
            "command":"wwx",
            "operator":[
                {"position":{"x": 0,"y":0,"z": 1,"d":0},"damage":10}
            ]
        },
        {
            "name":"swep",
            "command":"dx",
            "operator":[
                {"position":{"x": 1,"y":0,"z": 1,"d":0},"damage":1},
                {"position":{"x": 0,"y":0,"z": 1,"d":0},"damage":1},
                {"position":{"x":-1,"y":0,"z": 1,"d":0},"damage":1}
            ]
        },
        {
            "name":"hack",
            "command":"x",
            "operator":[
                {"position":{"x": 0,"y":0,"z": 1,"d":0},"damage":1}
            ]
        }
    ]
}